rocket_hub/__init__.py
rocket_hub/route.py
rocket_hub/handlers/__init__.py
rocket_hub/handlers/rocket_base.py
rocket_hub/handlers/system/__init__.py
rocket_hub/handlers/system/core.py
rocket_hub/handlers/system/file.py
rocket_hub/handlers/system/menu.py
rocket_hub/handlers/system/power.py
rocket_hub/handlers/system/product.py
rocket_hub/handlers/system/settings.py
rocket_hub/libs/__init__.py
rocket_hub/libs/geetest.py
rocket_hub/libs/file/__init__.py
rocket_hub/libs/file/bos.py
rocket_hub/libs/file/cos.py
rocket_hub/libs/file/ks3.py
rocket_hub/libs/file/oss2.py
rocket_hub/libs/file/s3.py
rocket_hub/libs/file/upload.py
rocket_hub/models/__init__.py
rocket_hub/models/dto_model.py
rocket_hub/models/enum.py
rocket_hub/models/hub_model.py
rocket_hub/models/power_model.py
rocket_hub/models/db_models/__init__.py
rocket_hub/models/db_models/file/__init__.py
rocket_hub/models/db_models/file/file_history_model.py
rocket_hub/models/db_models/file/file_resource_model.py
rocket_hub/models/db_models/file/file_restrict_model.py
rocket_hub/models/db_models/file/file_restrict_pic_model.py
rocket_hub/models/db_models/file/file_storage_path_model.py
rocket_hub/models/db_models/file/file_water_image_model.py
rocket_hub/models/db_models/log/__init__.py
rocket_hub/models/db_models/log/log_action_model.py
rocket_hub/models/db_models/menu/__init__.py
rocket_hub/models/db_models/menu/menu_cote_model.py
rocket_hub/models/db_models/menu/menu_info_model.py
rocket_hub/models/db_models/menu/menu_info_model_ex.py
rocket_hub/models/db_models/product/__init__.py
rocket_hub/models/db_models/product/product_info_model.py
rocket_hub/models/db_models/product/product_user_model.py
rocket_hub/models/db_models/role/__init__.py
rocket_hub/models/db_models/role/role_info_model.py
rocket_hub/models/db_models/role/role_power_model.py
rocket_hub/models/db_models/role/role_power_model_ex.py
rocket_hub/models/db_models/role/role_user_model.py
rocket_hub/models/db_models/settings/__init__.py
rocket_hub-1.0.1b1.dist-info/licenses/LICENSE
rocket_hub-1.0.1b1.dist-info/METADATA
rocket_hub-1.0.1b1.dist-info/WHEEL
rocket_hub-1.0.1b1.dist-info/top_level.txt
rocket_hub-1.0.1b1.dist-info/RECORD
